gcsam/__init__.py
gcsam/__main__.py
gcsam/excelHelpers.py
gcsam/graphs.py
gcsam/sampleManagement.py
gcsam/samplesInExcel.py
gcsam-0.0.4.dist-info/LICENSE
gcsam-0.0.4.dist-info/METADATA
gcsam-0.0.4.dist-info/WHEEL
gcsam-0.0.4.dist-info/entry_points.txt
gcsam-0.0.4.dist-info/top_level.txt
gcsam-0.0.4.dist-info/RECORD
