Metadata-Version: 2.1
Name: gcsam
Version: 0.0.4
Summary: Gas chromatography sample analyzer and manager
Home-page: https://github.com/eons44/gcsam
Author: eons
Author-email: eons@eons.dev
License: UNKNOWN
Project-URL: Bug Tracker, https://github.com/eons44/gcsam/issues
Platform: UNKNOWN
Classifier: Development Status :: 3 - Alpha
Classifier: Programming Language :: Python :: 3
Classifier: License :: OSI Approved :: MIT License
Classifier: Operating System :: OS Independent
Requires-Python: >=3.6
Requires-Dist: xlrd
Requires-Dist: xlsxwriter
Requires-Dist: matplotlib
